emailtogo/__init__.py
emailtogo/KNOWN_SERVICES
emailtogo/parse.py
emailtogo-0.0.1.dist-info/DESCRIPTION.rst
emailtogo-0.0.1.dist-info/METADATA
emailtogo-0.0.1.dist-info/metadata.json
emailtogo-0.0.1.dist-info/RECORD
emailtogo-0.0.1.dist-info/top_level.txt
emailtogo-0.0.1.dist-info/WHEEL
