Metadata-Version: 2.0
Name: emailtogo
Version: 0.0.1
Summary: Parse address of mail service from email address
Home-page: https://github.com/fanzeyi/emailtogo
Author: Zeyi Fan
Author-email: fanzeyi1994@gmail.com
License: Apache 2.0
Platform: UNKNOWN
Classifier: Development Status :: 1 - Planning
Classifier: Intended Audience :: Developers
Classifier: License :: OSI Approved :: Apache Software License
Classifier: Natural Language :: English
Classifier: Programming Language :: Python :: 2
Classifier: Programming Language :: Python :: 3
Classifier: Topic :: Communications :: Email
